adkt/__init__.py
sat/__init__.py
adkt-0.0.1.dist-info/METADATA
adkt-0.0.1.dist-info/WHEEL
adkt-0.0.1.dist-info/top_level.txt
adkt-0.0.1.dist-info/RECORD
