Metadata-Version: 2.4
Name: adkt
Version: 0.0.1
Summary: Wrapper To Create Telegram Bot For Agents Implemented With ADK
Author: Viacheslav Kovalevskyi
Author-email: viacheslav@kovalevskyi.com
License: MIT
Requires-Dist: python-dotenv==1.1
Requires-Dist: python-telegram-bot==22
Requires-Dist: google-adk==0.1.*
Dynamic: author
Dynamic: author-email
Dynamic: description
Dynamic: description-content-type
Dynamic: license
Dynamic: requires-dist
Dynamic: summary
